{
  "loginForm": {
    "title": "Grădina Botanică Alexandru Borza",
    "username": "Nume utilizator",
    "password": "Parolă",
    "loginButton": "Autentificare",
    "guestButton": "Vizualizare ca vizitator"
  },

  "employeePage": {
    "title": "Bun venit",
    "name": "Denumire",
    "type": "Tip",
    "species": "Specie",
    "carnivorous": "Plantă carnivoră",
    "zone": "Zonă",
    "head": "Criteriu",
    "addPl": "Adăugare plantă",
    "stats": "Statistici",
    "imageTH": "Imagine",
    "operationTH": "Operație",
    "filter": "Filtru",
    "criteria": "Criteriu",
    "loadImg": "Încarcă o imagine",
    "addPlBttn": "Adăugare"
  }
}
